mathlibdanval/__init__.py
mathlibdanval/cli.py
mathlibdanval/mathlib.py
mathlibdanval-1.1.1.dist-info/METADATA
mathlibdanval-1.1.1.dist-info/WHEEL
mathlibdanval-1.1.1.dist-info/entry_points.txt
mathlibdanval-1.1.1.dist-info/top_level.txt
mathlibdanval-1.1.1.dist-info/RECORD
