Metadata-Version: 2.4
Name: mathlibdanval
Version: 1.1.1
Summary: Mathematical functions library
Author: Daniel Valdez
License: MIT
Requires-Python: >=3.10
